motorturbine/__init__.py
motorturbine/collection.py
motorturbine/connection.py
motorturbine/document.py
motorturbine/errors.py
motorturbine/queryset.py
motorturbine/updateset.py
motorturbine/utils.py
motorturbine/fields/__init__.py
motorturbine/fields/base_field.py
motorturbine/fields/boolean_field.py
motorturbine/fields/date_field.py
motorturbine/fields/document_field.py
motorturbine/fields/float_field.py
motorturbine/fields/int_field.py
motorturbine/fields/list_field.py
motorturbine/fields/map_field.py
motorturbine/fields/objectid_field.py
motorturbine/fields/reference_field.py
motorturbine/fields/string_field.py
motorturbine-0.5.0.dist-info/METADATA
motorturbine-0.5.0.dist-info/RECORD
motorturbine-0.5.0.dist-info/WHEEL
motorturbine-0.5.0.dist-info/top_level.txt
