Metadata-Version: 2.1
Name: motorturbine
Version: 0.5.0
Summary: A ORM package for asyncio and motor
Home-page: http://github.com/BFriedrichs/motorturbine
Author: Björn Friedrichs
Author-email: bjoern@friedrichs1.de
License: MIT
Platform: UNKNOWN
Classifier: Development Status :: 2 - Pre-Alpha
Classifier: Intended Audience :: Developers
Classifier: Natural Language :: English
Classifier: Programming Language :: Python :: 3
Classifier: Programming Language :: Python :: 3.5
Classifier: Programming Language :: Python :: 3.6
Requires-Dist: motor (==1.2.2)
Requires-Dist: python-dateutil (==2.7.3)
